qwen_image_mps/__init__.py
qwen_image_mps/cli.py
qwen_image_mps/gradio_app.py
qwen_image_mps-0.7.2.dist-info/METADATA
qwen_image_mps-0.7.2.dist-info/WHEEL
qwen_image_mps-0.7.2.dist-info/entry_points.txt
qwen_image_mps-0.7.2.dist-info/licenses/LICENSE
qwen_image_mps-0.7.2.dist-info/RECORD
