Metadata-Version: 2.4
Name: qwen-image-mps
Version: 0.7.2
Summary: Generate and edit images with Qwen models on Apple Silicon (MPS) and other devices
Project-URL: Homepage, https://github.com/ivanfioravanti/qwen-image-mps
Project-URL: Repository, https://github.com/ivanfioravanti/qwen-image-mps
Project-URL: Issues, https://github.com/ivanfioravanti/qwen-image-mps/issues
Author-email: Ivan Fioravanti <ivanfioravanti@users.noreply.github.com>
License-Expression: MIT
License-File: LICENSE
Classifier: Development Status :: 4 - Beta
Classifier: Intended Audience :: Developers
Classifier: License :: OSI Approved :: MIT License
Classifier: Programming Language :: Python :: 3
Classifier: Programming Language :: Python :: 3.9
Classifier: Programming Language :: Python :: 3.10
Classifier: Programming Language :: Python :: 3.11
Classifier: Programming Language :: Python :: 3.12
Classifier: Programming Language :: Python :: 3.13
Classifier: Topic :: Multimedia :: Graphics
Classifier: Topic :: Scientific/Engineering :: Artificial Intelligence
Requires-Python: >=3.10
Requires-Dist: accelerate>=0.25.0
Requires-Dist: diffusers>=0.36
Requires-Dist: gguf>=0.10.0
Requires-Dist: gradio>=6.0.0
Requires-Dist: huggingface-hub>=0.20.0
Requires-Dist: pillow>=9.0.0
Requires-Dist: safetensors>=0.4.0
Requires-Dist: torch>=2.0.0
Requires-Dist: torchvision>=0.15.0
Requires-Dist: transformers>=4.35.0
Provides-Extra: dev
Requires-Dist: black; extra == 'dev'
Requires-Dist: isort; extra == 'dev'
Requires-Dist: pre-commit; extra == 'dev'
Requires-Dist: pytest>=8.4.1; extra == 'dev'
Requires-Dist: ruff; extra == 'dev'
